LICENSE
MANIFEST.in
README.md
package.json
setup.py
dash_new_tab/NewTab.py
dash_new_tab/__init__.py
dash_new_tab/_imports_.py
dash_new_tab/dash_new_tab.min.js
dash_new_tab/dash_new_tab.min.js.map
dash_new_tab/metadata.json
dash_new_tab/package-info.json
dash_new_tab.egg-info/PKG-INFO
dash_new_tab.egg-info/SOURCES.txt
dash_new_tab.egg-info/dependency_links.txt
dash_new_tab.egg-info/top_level.txt
tests/test_usage.py