Metadata-Version: 2.1
Name: dash_new_tab
Version: 0.0.2
Summary: Dash component that opens a URL in a new tab
Author: Michael Q <business@magicmq.dev>
License: MIT
Classifier: Framework :: Dash
License-File: LICENSE
